pylint_nautobot/__init__.py
pylint_nautobot/code_location_changes.py
pylint_nautobot/data/v2/v2-api-behavior-changes.yaml
pylint_nautobot/data/v2/v2-api-removed-fields.yaml
pylint_nautobot/data/v2/v2-api-renamed-fields.yaml
pylint_nautobot/data/v2/v2-code-location-changes.yaml
pylint_nautobot/data/v2/v2-database-behavior-changes.yaml
pylint_nautobot/data/v2/v2-database-removed-fields.yaml
pylint_nautobot/data/v2/v2-database-renamed-fields.yaml
pylint_nautobot/data/v2/v2-filters-corrected-fields.yaml
pylint_nautobot/data/v2/v2-filters-enhanced-fields.yaml
pylint_nautobot/data/v2/v2-filters-removed-fields.yaml
pylint_nautobot/data/v2/v2-filters-renamed-fields.yaml
pylint_nautobot/data/v2/v2-logging-renamed-loggers.yaml
pylint_nautobot/data/v3/v3-code-removals.yaml
pylint_nautobot/deprecated_classes.py
pylint_nautobot/deprecated_status_model.py
pylint_nautobot/dunder_filter_fields.py
pylint_nautobot/incorrect_base_class.py
pylint_nautobot/model_label.py
pylint_nautobot/q_search_filter.py
pylint_nautobot/replaced_models.py
pylint_nautobot/string_field_blank_null.py
pylint_nautobot/sub_class_name.py
pylint_nautobot/use_fields_all.py
pylint_nautobot/utils.py
pylint_nautobot-1.0.0.dist-info/METADATA
pylint_nautobot-1.0.0.dist-info/WHEEL
pylint_nautobot-1.0.0.dist-info/licenses/LICENSE
pylint_nautobot-1.0.0.dist-info/RECORD
