Metadata-Version: 2.4
Name: pylint-nautobot
Version: 1.0.0
Summary: Custom Pylint Rules for Nautobot
License: Apache-2.0
License-File: LICENSE
Keywords: nautobot,pylint
Author: Cristian Sirbu
Author-email: cristian.sirbu@networktocode.com
Requires-Python: >=3.10.0,<3.14
Classifier: Development Status :: 5 - Production/Stable
Classifier: Intended Audience :: Developers
Classifier: License :: OSI Approved :: Apache Software License
Classifier: Programming Language :: Python :: 3
Classifier: Programming Language :: Python :: 3.10
Classifier: Programming Language :: Python :: 3.11
Classifier: Programming Language :: Python :: 3.12
Classifier: Programming Language :: Python :: 3.13
Provides-Extra: all
Requires-Dist: importlib-resources (>=5.12.0)
Requires-Dist: pylint (>=4.0.4,<5.0)
Requires-Dist: pyyaml (>=6.0.1)
Requires-Dist: toml (>=0.10.2)
Project-URL: Homepage, https://github.com/nautobot/pylint-nautobot
Project-URL: Repository, https://github.com/nautobot/pylint-nautobot
